README.md
setup.cfg
setup.py
gym_puissance4/__init__.py
gym_puissance4.egg-info/PKG-INFO
gym_puissance4.egg-info/SOURCES.txt
gym_puissance4.egg-info/dependency_links.txt
gym_puissance4.egg-info/requires.txt
gym_puissance4.egg-info/top_level.txt
gym_puissance4/envs/__init__.py
gym_puissance4/envs/puissance4_env.py