Metadata-Version: 1.2
Name: gym-puissance4
Version: 0.11
Summary: Environement Gym pour le jeu Puissance4
Home-page: https://github.com/deleranax
Author: Deleranax
Author-email: deleranax@gmail.com
License: MIT
Keywords: gym,puissance4
Platform: UNKNOWN
Requires-Python: >=3.6
